haltia/__init__.py
haltia-0.0.1.dist-info/METADATA
haltia-0.0.1.dist-info/UNLICENSE
haltia-0.0.1.dist-info/WHEEL
haltia-0.0.1.dist-info/top_level.txt
haltia-0.0.1.dist-info/RECORD
